platformers/__init__.py
platformers/_mpu/__init__.py
platformers/_mpu/cross_entropy.py
platformers/_mpu/data.py
platformers/_mpu/initialize.py
platformers/_mpu/layers.py
platformers/_mpu/lora.py
platformers/_mpu/mappings.py
platformers/_mpu/random.py
platformers/_mpu/utils.py
platformers/fused_kernels/__init__.py
platformers/fused_kernels/compat.h
platformers/fused_kernels/scaled_masked_softmax.cpp
platformers/fused_kernels/scaled_masked_softmax.h
platformers/fused_kernels/scaled_masked_softmax_cuda.cu
platformers/fused_kernels/scaled_upper_triang_masked_softmax.cpp
platformers/fused_kernels/scaled_upper_triang_masked_softmax.h
platformers/fused_kernels/scaled_upper_triang_masked_softmax_cuda.cu
platformers/fused_kernels/setup.py
platformers/fused_kernels/tests/test_fused_kernels.py
platformers/fused_kernels/type_shim.h
platformers/generator/__init__.py
platformers/generator/generator.py
platformers/generator/generator_pipeline.py
platformers/hf/__init__.py
platformers/hf/aquila/model_utils.py
platformers/hf/aquila/modeling_aquila_hf.py
platformers/hf/aquila/predict.py
platformers/hf/baichuan/__init__.py
platformers/hf/baichuan/baichuan.py
platformers/hf/baichuan/tokenization_baichuan.py
platformers/hf/deberta/__init__.py
platformers/hf/deberta/deberta.py
platformers/hf/deberta/modeling_deberta.py
platformers/hf/deberta/modeling_deberta_rm_dev.py
platformers/hf/internlm/__init__.py
platformers/hf/internlm/tokenization_internlm.py
platformers/hf/llama/__init__.py
platformers/hf/llama/llama.py
platformers/hf/llama/llama_packing.py
platformers/hf/llama/llama_packing_pipe.py
platformers/hf/llama/llama_pipe.py
platformers/hf/llama/llama_rm_hf.py
platformers/hf/qwen/__init__.py
platformers/hf/qwen/modeling_qwen_hf.py
platformers/hf/qwen/tokenization_qwen.py
platformers/hf/unimc/__init__.py
platformers/hf/unimc/tokenization_unimc.py
platformers/hf/unimc/unimc.py
platformers/hf/yi/__init__.py
platformers/hf/yi/configuration_yi.py
platformers/hf/yi/tokenization_yi.py
platformers-0.1.0.dist-info/METADATA
platformers-0.1.0.dist-info/WHEEL
platformers-0.1.0.dist-info/RECORD
