Metadata-Version: 2.1
Name: platformers
Version: 0.1.0
Summary: 
Author: fecet
Author-email: xiezej@gmail.com
Requires-Python: >=3.10,<4.0
Classifier: Programming Language :: Python :: 3
Classifier: Programming Language :: Python :: 3.10
Classifier: Programming Language :: Python :: 3.11
Classifier: Programming Language :: Python :: 3.12
